sppd/__init__.py
sppd/__main__.py
sppd/sppd.py
sppd-0.1.2.dist-info/METADATA
sppd-0.1.2.dist-info/WHEEL
sppd-0.1.2.dist-info/entry_points.txt
sppd-0.1.2.dist-info/licenses/LICENSE
sppd-0.1.2.dist-info/RECORD
